[{"$5":777,"$20":999,"$10":888,"10c":222,"20c":333,"50c":444,"$100":2222,"$1":555,"5c":111,"$2":666,"$50":1111},{"0":"0,card,Sprite,4,person1","1":"1,card,Sprite,2,anonymous","3":"3,card,Doritos,15,person2","4":"4,card,Sprite,100,seller","5":"5,card,water,4,buyer1"},{"slotName":"A1","itemName":"water","itemCategory":"DRINK","slotCount":1,"itemPrice":1.5},{"slotName":"A2","itemName":"Sprite","itemCategory":"DRINK","slotCount":100,"itemPrice":2.0},{"slotName":"A3","itemName":"Doritos","itemCategory":"CHIPS","slotCount":55,"itemPrice":221.0}]